epages_client/__init__.py
epages_client/client.py
epages_client/http_handler.py
epages_client/method_mapping.json
epages_client/dataobjects/__init__.py
epages_client/dataobjects/address.py
epages_client/dataobjects/cart_create.py
epages_client/dataobjects/category_create.py
epages_client/dataobjects/category_sequence_update.py
epages_client/dataobjects/category_update.py
epages_client/dataobjects/contact_info.py
epages_client/dataobjects/content_page.py
epages_client/dataobjects/customer_create.py
epages_client/dataobjects/customer_update.py
epages_client/dataobjects/data_object.py
epages_client/dataobjects/enum_fetch_operator.py
epages_client/dataobjects/list_of_objects.py
epages_client/dataobjects/order_update.py
epages_client/dataobjects/product_create.py
epages_client/dataobjects/product_line_item_create.py
epages_client/dataobjects/product_line_item_update.py
epages_client/dataobjects/product_slideshow_sequence_update.py
epages_client/dataobjects/product_update.py
epages_client/dataobjects/remove_value.py
epages_client/dataobjects/script_tag_create.py
tests/__init__.py
tests/base_unit_test.py
tests/test_client.py
tests/test_client_carts_and_orders.py
tests/test_client_customer.py
tests/test_client_legal.py
tests/test_client_newsletter.py
tests/test_client_product.py
tests/test_client_script_tags.py
tests/test_dataobject_address.py
tests/test_dataobject_cart_create.py
tests/test_dataobject_category_create.py
tests/test_dataobject_category_sequence_update.py
tests/test_dataobject_category_update.py
tests/test_dataobject_contact_info.py
tests/test_dataobject_content_page.py
tests/test_dataobject_customer_create.py
tests/test_dataobject_customer_update.py
tests/test_dataobject_order_update.py
tests/test_dataobject_product_create.py
tests/test_dataobject_product_line_item_create.py
tests/test_dataobject_product_line_item_update.py
tests/test_dataobject_product_update.py
tests/test_dataobject_tag_create.py
tests/resources/test.jpg
tests/resources/test2.jpg
epages_client-0.2.0.dist-info/AUTHORS.rst
epages_client-0.2.0.dist-info/LICENSE
epages_client-0.2.0.dist-info/METADATA
epages_client-0.2.0.dist-info/WHEEL
epages_client-0.2.0.dist-info/top_level.txt
epages_client-0.2.0.dist-info/RECORD
