Metadata-Version: 2.1
Name: epages-client
Version: 0.2.0
Summary: Python client for ePages REST API.
Home-page: https://github.com/vilkasgroup/epages_client
Author: Pekka Piispanen, Tero Kotti
Author-email: pekka@vilkas.fi, tero@vilkas.fi
License: MIT license
Keywords: epages_client
Platform: UNKNOWN
Classifier: Development Status :: 4 - Beta
Classifier: Intended Audience :: Developers
Classifier: License :: OSI Approved :: MIT License
Classifier: Natural Language :: English
Classifier: Programming Language :: Python :: 3.6
Requires-Dist: requests
Requires-Dist: validators
